LICENSE
MANIFEST.in
README.rst
requirements.txt
setup.py
chembl_client/__init__.py
chembl_client/elastic_client.py
chembl_client/http_errors.py
chembl_client/new_client.py
chembl_client/query.py
chembl_client/query_set.py
chembl_client/settings.py
chembl_client/singleton.py
chembl_client/spore_client.py
chembl_client/test_docs_examples.py
chembl_client/test_utils.py
chembl_client/tests.py
chembl_client/unichem.py
chembl_client/url_query.py
chembl_client/utils.py
chembl_client.egg-info/PKG-INFO
chembl_client.egg-info/SOURCES.txt
chembl_client.egg-info/dependency_links.txt
chembl_client.egg-info/entry_points.txt
chembl_client.egg-info/not-zip-safe
chembl_client.egg-info/requires.txt
chembl_client.egg-info/top_level.txt
chembl_client/scripts/__init__.py
chembl_client/scripts/chembl_act.py
chembl_client/scripts/chembl_ids.py
chembl_client/scripts/chembl_m2t.py
chembl_client/scripts/chembl_sim.py
chembl_client/scripts/chembl_sub.py
chembl_client/scripts/chembl_t2m.py
chembl_client/scripts/utils.py