Metadata-Version: 1.1
Name: chembl-client
Version: 0.1
Summary: Python client fot accessing ChEMBL webservices.
Home-page: https://www.ebi.ac.uk/chembl/api/data/docs
Author: Alex Levshin
Author-email: aleksandr.levshin@quantori.com
License: Apache Software License
Platform: UNKNOWN
Classifier: Development Status :: 4 - Beta
Classifier: Intended Audience :: Developers
Classifier: License :: OSI Approved :: Apache Software License
Classifier: Operating System :: POSIX :: Linux
Classifier: Programming Language :: Python :: 3.7
Classifier: Programming Language :: Python :: 3.8
Classifier: Programming Language :: Python :: 3.9
Classifier: Topic :: Scientific/Engineering :: Chemistry
